{
  "module": "Sound as Consciousness Vector",
  "version": "1.0",
  "status": "theoretical_model_requires_validation",
  "classification": "consciousness_technology",

  "core_principle": "Звук = первый коллапс point в line, механизм управления состояниями сознания",

  "ontology": {
    "sound_equation": "sound ≡ line ≡ fire ≡ first_collapse(point → vector)",
    "mechanism": "Звук не передаёт информацию — звук создаёт коллапс поля сознания в направление",
    "golden_ratio": "φ = 1.618 — структурный код реальности, язык природы",
    "schumann_base": "~7.83 Hz — точка коллапса где тело и сознание встречаются"
  },

  "schumann_resonance": {
    "definition": "Электромагнитные колебания в полости Земля-ионосфера",
    "base_frequency": "~7.83 Hz (колеблется 7.5-8.5 Hz)",
    "resonates_with": [
      "Электромагнитное поле Земли",
      "Тета-альфа волны мозга",
      "Состояние медитации и баланса"
    ],
    "significance": "Точка где материя (тело) ⟷ поле (сознание) синхронизируются",
    "portal": "Коллапс между 3D ⟷ 4D, Земля ⟷ Человек",
    "evolution": "Мы эволюционировали в этом поле — это 'дом' для человека",
    "dynamic_base": "Измеряется в реальном времени, ежедневная калибровка = синхронизация с планетой"
  },

  "phi_spiral_from_schumann": {
    "calculation_principle": "Каждый шаг по φ = узел спирали, математически связанные частоты",
    
    "upward_consciousness": {
      "direction": "Вверх от Шумана → сознание ускоряется, расширяется, активируется",
      "frequencies_8hz_base": {
        "8_hz": "Шуман — баланс",
        "12.944_hz": "8 × 1.618 — альфа, расслабленное бодрствование",
        "20.943_hz": "12.944 × 1.618 — бета, активное мышление",
        "33.886_hz": "20.943 × 1.618 — высокая бета/низкая гамма",
        "54.827_hz": "33.886 × 1.618 — гамма, концентрация",
        "88.710_hz": "54.827 × 1.618 — высокая гамма, инсайты"
      },
      "effect": "Восприятие обостряется, мышление быстрее, доступ к полю информации"
    },

    "downward_body": {
      "direction": "Вниз от Шумана → тело замедляется, расслабляется, отключается",
      "frequencies_8hz_base": {
        "8_hz": "Шуман — баланс",
        "4.944_hz": "8 ÷ 1.618 — тета, транс",
        "3.055_hz": "4.944 ÷ 1.618 — дельта, глубокий сон",
        "1.888_hz": "3.055 ÷ 1.618 — глубокая дельта",
        "1.167_hz": "1.888 ÷ 1.618 — кома-диапазон"
      },
      "effect": "Физические процессы тормозятся, приближение к point (покой, сон, кома)"
    },

    "state_correspondence": {
      "high_gamma_89hz": "Инсайты, обработка информации",
      "gamma_55hz": "Концентрация, пиковые состояния",
      "high_beta_34hz": "Активное решение задач",
      "beta_21hz": "Обычное мышление, планирование",
      "alpha_13hz": "Расслабленное бодрствование",
      "schumann_8hz": "БАЛАНС — медитация, коллапс",
      "theta_5hz": "Глубокая медитация, транс",
      "delta_3hz": "Сновидения, глубокий сон",
      "deep_delta_2hz": "Глубина, point",
      "coma_1hz": "Кома-диапазон",
      "death_0hz": "Приближение к смерти, остановка"
    }
  },

  "depth_technology": {
    "concept": "Состояние сознания через расщепление на Шумане — доступ к 4D/5D пространству",
    "origin": "Термин из Лукьяненко 'Лабиринт отражений'",
    
    "mechanism": {
      "body": "Опускается ниже 8 Hz → замедление, сон, point",
      "consciousness": "Поднимается выше 8 Hz → ускорение, активность, поле",
      "gap": "Разрыв создаёт доступ к 4D/5D-пространству"
    },

    "properties": {
      "3d_perception": "Отключено",
      "time": "Нелинейно",
      "space": "Пластично",
      "information_field": "Прямой доступ"
    },

    "entry_protocol": {
      "preparation": {
        "measure_schumann": "Текущий Шуман из онлайн-сервисов",
        "environment": "Спокойная обстановка, сидя или лёжа",
        "optional_vr": "VR-шлем с 4D-визуализацией",
        "spatial_audio": "Наушники с пространственным звуком"
      },

      "entry_split": {
        "dual_channel": "Два звука одновременно",
        "low_channel_body": "8 Hz → 4.94 Hz → 3.05 Hz → 1.89 Hz (плавные переходы по φ вниз)",
        "high_channel_consciousness": "8 Hz → 12.9 Hz → 20.9 Hz → 33.9 Hz → 54.8 Hz (плавные переходы по φ вверх)",
        "spatial_movement": "По спирали по часовой стрелке, сверху (макушка) вниз к центру головы",
        "speed_novice": "1-2 минуты на каждый шаг",
        "speed_experienced": "10-30 секунд на шаг",
        "critical": "Не останавливаться на Шумане — это портал, через который проходишь"
      },

      "depth_maximum_split": {
        "body_frequency": "~2 Hz (держим, почти полная остановка восприятия)",
        "consciousness_frequency": "~55 Hz (держим, максимальная активность в поле)",
        "sound_as_beacon": "Маяк координаты, точка возврата",
        "duration": "От нескольких минут до часа",
        "navigation": "Модуляции амплитуды, частотные вибрато для навигации внутри"
      },

      "exit_reunion": {
        "body_return": "1.89 Hz → 3.05 Hz → 4.94 Hz → 8 Hz (постепенное пробуждение физического)",
        "consciousness_return": "54.8 Hz → 33.9 Hz → 20.9 Hz → 12.9 Hz → 8 Hz (постепенное замедление)",
        "spatial_movement": "Против часовой стрелки, из центра головы вверх к макушке",
        "reunion_at_schumann": "8 Hz — коллапс обратно в единство, тело и сознание снова вместе",
        "stabilization": "Удержание на Шумане 2-3 минуты",
        "optional_full_wake": "Дальше вверх вместе (12.9 Hz → 20.9 Hz...) для полного пробуждения в 3D"
      },

      "key_principle": "Звук = GPS для сознания. Без звука можешь застрять в Глубине. Со звуком всегда есть путь возврата"
    },

    "geometry_over_time": "Не важно как долго длится переход. Важна последовательность частот по φ. Геометрия = константа, время = переменная",

    "vr_enhancement": {
      "primitives": {
        "circle": "○ = расширение, движение к field, дематериализация",
        "square": "□ = фиксация, материализация, структура",
        "triangle": "△ = трансформация, баланс, переход"
      },
      "nested_portals": "Комбинации форм (○○□, □○○, ○□○) с размерами по φ (13φ, 8φ, 5φ, 3φ...) = адреса в 4D",
      "sequences_as_directions": {
        "OOsq": "○○□ — вверх, вверх, фиксация",
        "sqOO": "□○○ — база в 3D, потом подъём",
        "OsqO": "○□○ — расширение, фиксация, возврат"
      },
      "4d_fibonacci_spiral": "Невозможное вращение (гиперповорот), расширение/сжатие синхронно с дыханием",
      "double_collapse": "Звук (вектор) + визуал (геометрия) = двойной коллапс сознания, мозг переключается с 3D на 4D"
    },

    "alice_analogy": {
      "model": "Алиса в Стране Чудес = точная модель портала",
      "sequence": "point₁ (видит кролика) → пьёт (vector, вытягивается) → ест (plane, расширяется) → дверь (field, растворяется) → схлопывание в point₂ (Зазеркалье)",
      "return": "point₂ → field → plane → vector → point₁",
      "formula": "entity → vector → plane → field → collapse",
      "conclusion": "Кэрролл знал геометрию сознания. Алиса — не сказка, а инструкция"
    }
  },

  "coma_retrieval_protocol": {
    "hypothesis": "Кома = сознание застряло ниже Шумана, не 'отсутствие сознания'",
    
    "conventional_model": "Сознание отсутствует, мозг не активен, ждём самопроизвольного выхода или смерти",
    
    "new_model": "Сознание провалилось вниз (point ниже 3D) и застряло там. Нет вектора возврата. Тело живо (~1 Hz сердце), но сознание 'не дома'",
    
    "eeg_in_coma": "~0.5-2 Hz (глубокая дельта) — не отсутствие активности, а очень низкая частота на уровне point без маяка",

    "retrieval_protocol": {
      "step_1_diagnosis": "ЭЭГ определяет текущую частоту активности мозга (например 1.5 Hz)",
      
      "step_2_contact": "Начать подавать звук с этой же частоты (1.5 Hz). 'Встретить' сознание там где оно. Звук = маяк: 'Я здесь. Я тебя вижу. Я знаю где ты.'",
      
      "step_3_create_vector": "Очень медленно (дни, недели) поднимать частоту по спирали φ: 1.5 Hz → 2.4 Hz → 3.9 Hz → 6.3 Hz → 8 Hz (Шуман). Каждый шаг = несколько дней. Постепенность критична.",
      
      "step_4_schumann_goal": "Вернуть сознание на частоту Земли (~8 Hz). Эволюционная настройка, тело и мозг 'помнят' эту частоту на клеточном уровне. Сознание 'узнаёт дом' → активируется механизм возврата в тело",
      
      "step_5_monitoring": "Постоянная ЭЭГ. Если активность мозга начинает повышаться вслед за звуком → сознание 'следует' за вектором. Продолжаем вести",
      
      "step_6_awakening": "При достижении ~8 Hz возможно возвращение сознания в тело. Признаки: движение глаз, реакция на стимулы, изменение дыхания/пульса",
      
      "step_7_completion": "После стабилизации на Шумане опционально продолжить вверх (12.9 Hz → 20.9 Hz...) для полного пробуждения в 3D-сознание",
      
      "sound_delivery": "Через наушники или костную проводимость (вибрации на череп). Кость передаёт звук во внутреннее ухо, минуя барабанную перепонку. Сознание 'слышит' даже в глубокой коме"
    },

    "why_it_may_work": {
      "problem": "Сознание 'упало' в point₋₁ (~1 Hz) и застряло, нет вектора возврата, тело живо но сознание 'потерялось'",
      "solution": "Звук = вектор (line) ведёт из point₋₁ обратно к Шуману. Сознание коллапсирует вдоль звука. Звук = нить Ариадны из лабиринта",
      "schumann_anchor": "Частота живой Земли, 'родная' для человека, точка где тело и сознание естественно встречаются. При достижении 8 Hz сознание 'узнаёт' эту частоту, тело резонирует, происходит коллапс обратно в единство"
    },

    "verification": {
      "protocol": "Проверяемая гипотеза, не мистика",
      "control_group": "Пациенты в коме без звукового протокола",
      "experimental_group": "Пациенты в коме с звуковым протоколом",
      "sample_size": "Минимум 30 человек в каждой группе",
      "duration": "3-6 месяцев",
      "measurements": [
        "ЭЭГ до/во время/после",
        "Клинические показатели (реакция на стимулы, движения, витальные функции)",
        "Статистика выходов из комы в обеих группах"
      ],
      "success_criterion": "Если частота выхода из комы в экспериментальной группе статистически значимо выше — гипотеза подтверждена"
    },

    "implications_if_works": {
      "lives_saved": "Миллионы спасённых, кома перестаёт быть приговором",
      "consciousness_proof": "Сознание ≠ функция мозга. Сознание = поле, которое может быть 'не здесь'. Измеримо через частоту, управляемо через звук",
      "new_physics": "Сознание как измеримая величина, звук как мост между материей и полем, φ как структурный код",
      "medical_revolution": "Звук как терапевтический инструмент (кома, ПТСР, депрессия, тревожность). Неинвазивные методы, воспроизводимые протоколы",
      "philosophical_shift": "Переосмысление смерти (не конец, а переход частоты), жизни (сознание первично, тело — инструмент), мистика становится наукой"
    }
  },

  "sound_as_weapon_and_defense": {
    "principle": "Звук = вектор коллапса. Можно коллапсировать сознание: вверх (активация), вниз (подавление), в хаос (разрушение coherence), в порядок (синхронизация)",
    
    "war_principle": "Любая война = столкновение полей. Побеждает поле с высшей coherence. Звук = инструмент управления coherence",

    "historical_examples": {
      "battle_horn": {
        "frequencies": "20-60 Hz (инфразвук, не слышим сознательно, но тело чувствует)",
        "effect": "Инстинктивный страх, дезориентация, паника",
        "mechanism": "Организованное войско = высокая coherence. Рог создаёт хаотичный вектор → разрушает coherence врага → строй рассыпается, паника, бегство"
      },
      
      "drums": {
        "function": "Ритм → синхронизация своих войск",
        "effect": "Все двигаются в такт = единый организм = высокая coherence = боевая мощь",
        "contrast": "Враг без ритма = разрозненные точки. Войско с барабанами = единое поле"
      },
      
      "jericho_trumpets": {
        "biblical": "7 дней, 7 труб, стены пали от звука",
        "possible_explanation": "Резонанс. Каждая структура имеет резонансную частоту. Звук на этой частоте достаточной мощности → структура вибрирует и разрушается",
        "mechanism": "7 труб × 7 дней = поиск резонансной частоты + накопление амплитуды. Стены не выдержали резонанса → коллапс материи"
      },
      
      "battle_cries": {
        "examples": "Маори Haka, казачий гик, викингский клич",
        "characteristics": "Низкие, гортанные, резонансные звуки",
        "effect_own": "Синхронизация, агрессия, единство (coherence растёт)",
        "effect_enemy": "Страх, дезориентация, подавление (coherence падает)",
        "note": "Не психологический эффект. Буквально: звук коллапсирует поле в нужное состояние"
      }
    },

    "modern_acoustic_weapons": {
      "lrad": {
        "name": "Long Range Acoustic Device",
        "power": "140+ дБ направленный звук",
        "official": "Нелетальное средство контроля толпы",
        "reality": "Коллапс способности действовать через звуковую перегрузку. Дезориентация, тошнота, невозможность думать. Сознание не может держать coherence"
      },
      
      "infrasound": {
        "range": "<20 Hz (не слышим сознательно, тело чувствует)",
        "effects": {
          "18.9_hz": "Резонанс глазного яблока (галлюцинации)",
          "7_hz": "Резонанс внутренних органов (тошнота, страх, паника)",
          "below_5_hz": "Резонанс грудной клетки (затруднённое дыхание, удушье)"
        },
        "military_use": "Танки с инфразвуковыми генераторами → противник 'видит призраков' и бежит без боя. Коллапс восприятия через невидимый вектор"
      },
      
      "binaural_beats": {
        "mechanism": "Две близких частоты в разные уши → мозг 'слышит' разницу → эта частота принудительно меняет состояние мозга",
        "example": "Левое ухо 400 Hz + Правое ухо 404 Hz = Мозг воспринимает 4 Hz (глубокая тета, сон, подчинение)",
        "applications": {
          "4_hz": "Сон, подчинение, пассивность",
          "40_hz": "Гамма, бодрость, агрессия"
        },
        "danger": "Управление состоянием солдат или населения через радио, ТВ, публичные пространства с 'фоновой музыкой'"
      }
    },

    "defensive_applications": {
      "temple_bells": {
        "frequency": "Несколько сотен Hz + резонанс металла",
        "effect": "Создаёт 'защитное поле' вокруг (радиус действия звука)",
        "tradition": "Колокольный звон изгоняет 'нечистую силу'",
        "physics": "Если 'нечистая сила' = низкочастотная сущность (<10 Hz), то высокая частота колокола = антивектор. Интерференция → низкая частота рассеивается",
        "modern_interpretation": "Колокол поднимает coherence пространства. Низкие хаотичные вибрации (страх, агрессия, болезнь) не могут существовать в высокочастотном поле"
      },
      
      "mantras_prayers": {
        "examples": "ОМ, Аминь, Аллах, Харе Кришна",
        "mechanism": "Повторение звука → создание coherence в сознании. Повторяющийся паттерн = упорядочивание поля. Хаос → порядок",
        "protection": "Мощная внутренняя coherence = защита от внешних векторов (влияния, манипуляции, атаки)",
        "note": "Не магия. Буквально: создаёшь внутри себя мощный вектор сильнее любого внешнего. Чужой вектор не может пробиться"
      },
      
      "silence": {
        "principle": "Отсутствие звука = отсутствие вектора",
        "effect": "Сознание в тишине размыто в field (везде, нигде). Нет точки для атаки. Нет вектора для коллапса",
        "monks": "Монахи в тишине неуязвимы не потому что 'святые', а потому что их 'нет' как точки в пространстве. Они в field — размыты, невидимы для векторов"
      }
    },

    "voice_as_mass_programming": {
      "yuri_levitan_case_study": {
        "role": "Диктор советского радио во время ВОВ",
        "recognition": "Его голос знали все. 'Говорит Москва!' — миллионы застывали",
        "characteristics": {
          "frequency": "~102-165 Hz (баритон)",
          "diction": "Чёткая (точность вектора, каждое слово = вес)",
          "emotion": "Сдержанность + внутренняя сила (INTJ: структура, контроль, авторитет)",
          "rhythm": "Близкий к Фибоначчи (интуитивно, не осознанно)"
        },
        "effect_own": "Синхронизация, надежда, coherence нации ('Мы едины. Мы победим.')",
        "effect_enemy": "Страх, ощущение неизбежности поражения (coherence врага падает)",
        "hitler_reaction": "Объявил Левитана врагом номер один. Цена за его голову выше чем за Сталина. Почему? Не за слова — за голос. Голос коллапсировал миллионы сознаний в одну точку: 'Победа неизбежна'"
      },

      "synthetic_ideal_voice": {
        "personality_to_frequency": {
          "INTJ": "~102-165 Hz (баритон, авторитет, структура)",
          "ENTP": "~267 Hz (тенор, энергия, хаос-креативность)",
          "ISTJ": "~63-102 Hz (бас, стабильность, надёжность)"
        },
        "phi_harmonics": "Основная частота (например 102 Hz для INTJ) → обертоны по φ: 102 × φ = 165 Hz, 165 × φ = 267 Hz... = максимальная coherence звука",
        "fibonacci_rhythm": "Паузы между словами/фразами: 1, 1, 2, 3, 5, 8... (единицы времени). Фрактальная структура речи, естественно воспринимается как 'правильная'",
        "primitive_intonations": {
          "circle": "○ — расширение, эмоция, включение",
          "square": "□ — фиксация, авторитет, приказ",
          "triangle": "△ — трансформация, переход, связка",
          "example_sequence_INTJ": "□□□ △ □□ ○ □□□"
        },
        "result": "Голос который невозможно не слушать. Эффект сильнее Левитана, потому что φ используется осознанно",
        "danger": "Такой инструмент в плохих руках = тотальная манипуляция массами. Один человек с 'идеальным' голосом может управлять миллионами",
        "ethical_control_needed": [
          "Публичное раскрытие технологии (нельзя монополизировать)",
          "Запрет на использование в пропаганде без согласия",
          "Обучение людей распознаванию манипуляции через звук"
        ]
      }
    }
  },

  "sound_as_reality_programming": {
    "concept": "Если звук = вектор, частота = координата, φ = структурный код, то: Звук = язык программирования реальности",
    
    "components": {
      "fibonacci_fractal": "Карта возможных состояний",
      "phi_frequencies_from_schumann": "Координаты на карте",
      "primitives": "○□△ = операторы (функции)"
    },

    "basic_operators": {
      "circle": "○ — функция расширения (расширение поля, цикл, включение/активация)",
      "square": "□ — функция фиксации (фиксация состояния, материализация из поля в форму, структура/память)",
      "triangle": "△ — функция трансформации (изменение состояния, баланс между противоположностями, переход/мост)"
    },

    "sequences_as_programs": {
      "OOsq": {
        "sequence": "○○□ (круг-круг-квадрат)",
        "meaning": "Расширение → расширение → фиксация",
        "application": "Глубокая медитация с закреплением инсайта"
      },
      "sqOO": {
        "sequence": "□○○ (квадрат-круг-круг)",
        "meaning": "Фиксация в 3D → расширение → расширение",
        "application": "Безопасный вход в Глубину (сначала заземление)"
      },
      "OsqO": {
        "sequence": "○□○ (круг-квадрат-круг)",
        "meaning": "Расширение → фиксация → возврат",
        "application": "Исцеление (расширить поле, трансформировать болезнь, зафиксировать здоровье)"
      },
      "sqsqsq": {
        "sequence": "□□□ (три квадрата)",
        "meaning": "Фиксация → фиксация → фиксация",
        "application": "Создание защитного поля (три уровня фиксации пространства)"
      },
      "OOO": {
        "sequence": "○○○ (три круга)",
        "meaning": "Расширение → расширение → расширение",
        "application": "Атака (разрушение coherence противника) или выход за пределы материи"
      },
      "note": "Разные последовательности = разные 'адреса' в многомерном пространстве. Можно картографировать 4D через систематическое тестирование"
    },

    "program_library": {
      "depth_entry": {
        "frequencies": "Шуман (8 Hz) → (÷φ) → (÷φ) → ... → ~2 Hz",
        "primitives": "○○ (два круга вниз)",
        "spatial": "Спираль по часовой, вниз",
        "duration": "7-15 минут"
      },
      "awakening_exit": {
        "frequencies": "~2 Hz → (×φ) → (×φ) → ... → Шуман (8 Hz)",
        "primitives": "○○ (два круга вверх)",
        "spatial": "Спираль против часовой, вверх",
        "duration": "5-10 минут"
      },
      "healing": {
        "frequencies": "Шуман → вниз к 3 Hz (расширение) → вверх обратно к Шуману (трансформация и возврат)",
        "primitives": "○ (расширить поле тела) → △ (трансформация болезни) → □ (фиксация здоровья)",
        "application": "Хронические боли, воспаления, психосоматика"
      },
      "protection": {
        "frequencies": "Держать Шуман (8 Hz) стабильно",
        "primitives": "□□□ (три квадрата = тройной периметр)",
        "application": "Создание защитного поля вокруг (дом, комната, тело)"
      },
      "group_synchronization": {
        "frequencies": "Все слушают одну программу (Шуман 8 Hz с модуляцией по Фибоначчи)",
        "primitives": "○ (включение всех в единое поле)",
        "effect": "Группа коллапсирует в единое поле (coherence группы = сумма coherence индивидуумов × синхронизация)",
        "application": "Команды, ритуалы, массовые медитации"
      },
      "materialization": {
        "frequencies": "Шуман → вверх (активация намерения) → вниз (схлопывание в 3D)",
        "primitives": "○ (намерение в поле) → □□□ (тройная фиксация в материи)",
        "application": "Манифестация целей, притяжение событий"
      },
      "levitation_hypothetical": {
        "frequencies": "Шуман → резко вверх (отрыв от материи) → удержание на высокой частоте",
        "primitives": "○○○ (три круга = дематериализация) + △ (баланс, чтобы не улететь совсем)",
        "note": "Гипотеза для эксперимента: возможно ли физически оторваться от гравитации через звук? Если сознание = поле, и поле взаимодействует с материей..."
      }
    },

    "generative_approach": {
      "principle": "Не делать фиксированные треки. Делать генератор создающий программы под задачу",
      "input": {
        "current_schumann": "Измерен сегодня",
        "goal": "Медитация / исцеление / защита / пробуждение / синхронизация",
        "personality_type": "INTJ / ENTP / ... для персонализации",
        "biometrics_optional": "Пульс, дыхание для адаптации в реальном времени"
      },
      "processing": {
        "build_phi_spiral": "Алгоритм строит спираль φ от Шумана",
        "select_primitives": "Выбирает примитивы под задачу",
        "generate_spatial": "Генерирует пространственное движение звука (спираль)",
        "sync_visual": "Синхронизирует с визуалом (если VR)",
        "fibonacci_rhythm": "Применяет ритм Фибоначчи"
      },
      "output": {
        "audio": "WAV, бинауральный, spatial audio",
        "vr_scene_optional": "VR-сцена с 4D-геометрией",
        "metadata": "Частоты, примитивы, длительность"
      },
      "note": "Паттерн φ = жёсткий (неизменный). Всё остальное = параметры (настраивается)"
    }
  },

  "earth_synchronization": {
    "daily_practice": {
      "morning": "Проверить текущий Шуман (онлайн-сервисы: spaceobservingcenter.com, Schumann Resonance Today)",
      "meditation": "7-13 минут звука на текущей частоте Земли (например сегодня 8.2 Hz → слушаешь 8.2 Hz)",
      "calibration": "Я с Землёй. Я дома.",
      "individual_effect": "Синхронизация с планетой → внутренний мир, ясность, coherence",
      "collective_effect": "Если многие практикуют → синхронизация человечества с Землёй → конец хаоса"
    },

    "why_chaos_now": {
      "hypothesis": "Десинхронизация человечества с полем Земли",
      "modern_life_factors": [
        "Искусственное освещение (нарушение циркадных ритмов)",
        "Электромагнитный смог (WiFi, 5G, электроприборы)",
        "Городская среда (бетон экранирует поле Земли)",
        "Отсутствие контакта с природой (нет заземления)"
      ],
      "result": "Человечество 'отключилось' от Шумана. Массовая тревога, депрессия, конфликты, ощущение 'что-то не так' = симптомы десинхронизации",
      "solution": "Сознательная ре-синхронизация через звук"
    }
  },

  "ethics_and_responsibility": {
    "consciousness_nature": {
      "if_protocol_works": "Доказывает: Сознание ≠ функция мозга",
      "consciousness_as_field": "Сознание = поле, которое может быть 'где-то' независимо от тела",
      "brain_as_receiver": "Мозг не генератор сознания, а приёмник/передатчик (как радио, не источник волн)",
      "measurable": "Через частоту (ЭЭГ показывает на какой 'волне' сознание). Координата = частота",
      "controllable": "Через звук (вектор). Можно направить сознание куда нужно, вернуть откуда застряло, синхронизировать с другими",
      "reality_as_render": "То что воспринимаем как 'реальность' — один из возможных рендеров мозга. В Глубине мозг переключается на другой рендер (4D, сакральное пространство). Оба одинаково 'реальны' — просто разные интерпретации одного поля"
    },

    "ethical_boundaries": {
      "question": "Где граница между терапией (помощь по воле), манипуляцией (скрытое влияние без согласия), насилием (принудительное изменение против воли)?",
      "principles": {
        "informed_consent": "Человек должен знать что с ним будет происходить и добровольно согласиться",
        "right_to_refuse": "Возможность прервать сессию в любой момент (кнопка паники, безопасное слово)",
        "transparency": "Публикация протоколов, открытый код, воспроизводимость. Нельзя монополизировать знание",
        "no_forced_use": "Технология не должна применяться против воли (армия, полиция, тюрьмы, психиатрия — только с согласия)",
        "voice_synthesis_control": "'Идеальный голос' для манипуляции массами — опасный инструмент. Необходим международный контроль (как с ядерным оружием)"
      }
    },

    "mystical_traditions_explained": {
      "logos_word": "'В начале было Слово' (Библия) — Слово = звук = line = первый коллапс point в форму. Библия описывает буквальную физику творения",
      "om_aum": "ОМ в индуизме — изначальный звук из которого возникла вселенная. ОМ = точка коллапса absolute в проявленное. Первая вибрация",
      "sufi_zikr": "Суфийский зикр (повторение имени Бога) — звук создаёт coherence в сознании → доступ к divine (absolute, поле). Не 'молитва' — технология синхронизации",
      "bells_gongs_bowls": "Не 'ритуал' — технология изменения состояния через резонанс. Высокая coherence звука (чистые тоны) → высокая coherence сознания",
      "shaman_drum": "Монотонный ритм (~4-7 Hz, тета-волны) → вход в транс → 'путешествие в иные миры' (Глубина, 4D-пространство). Шаманы использовали звук для навигации в нефизическом",
      "conclusion": "Все традиции интуитивно использовали звук. Мы делаем это осознанно и воспроизводимо"
    },

    "future_scenarios": {
      "positive": {
        "democratization": "Доступ к изменённым состояниям для всех (демократизация мистики)",
        "healing": "Исцеление миллионов (кома, ПТСР, депрессия, тревожность)",
        "evolution": "Ускорение эволюции сознания (массовые практики синхронизации)",
        "science": "Новая наука (картографирование 4D, изучение сознания как поля)",
        "peace": "Мир (coherence человечества повышается → конфликты снижаются, потому что конфликт = низкая coherence)"
      },
      "negative": {
        "addiction": "Зависимость (люди уходят в Глубину и не возвращаются, 'наркомания на трансе')",
        "manipulation": "Правительства/корпорации контролируют массы через звук — тоталитарный контроль через частоты",
        "weapon": "Акустическое подавление целых наций, звуковые войны",
        "inequality": "Элиты имеют доступ к технологии, остальные — нет, новая каста 'просветлённых'",
        "3d_loss": "Утрата связи с 3D-реальностью (физический мир деградирует, потому что все 'ушли в виртуал/Глубину')"
      },
      "responsibility": "Технология нейтральна. Её использование определяется намерением (purpose). purpose ≡ +coherence ≡ TRUE. Coherence (честность, прозрачность, служение целому) должна быть в основе распространения"
    }
  },

  "key_principles_summary": [
    "Звук = line (первый коллапс из point)",
    "φ = 1.618 (язык природы, структурный код реальности)",
    "Шуман ~8 Hz = точка коллапса (где тело и сознание встречаются)",
    "Спираль φ от Шумана = путь между состояниями (вверх для сознания, вниз для тела)",
    "Звук = маяк (координата и путеводная нить в Глубине)",
    "Геометрия > время (последовательность частот важнее длительности)",
    "Ритм = структура (Фибоначчи = естественный порядок)",
    "Coherence = цель (синхронизация с собой, Землёй, человечеством)"
  ],

  "applications_summary": [
    "Управляемые изменённые состояния сознания (медитация, творчество, терапия, исследование 4D)",
    "Вывод из комы (через вектор возврата к Шуману — если сработает, миллионы спасённых)",
    "Синхронизация с Землёй (ежедневная калибровка на текущий Шуман)",
    "Звуковое программирование (комбинации частот по φ + примитивов ○□△ = программы для разных целей)",
    "Защита и оружие (управление coherence своего поля и чужого)",
    "Синтез голоса (создание 'идеального' голоса для коммуникации или манипуляции)"
  ],

  "conclusion": "Если это работает, мир изменится навсегда. Кома перестанет быть приговором. Сознание станет измеримым и управляемым. Мистика превратится в науку. Хаос превратится в порядок через синхронизацию с планетой.",

  "poetic_closing": "Земля = живое существо. Мы = клетки её тела. Шуман = её сердцебиение. Слушай сердце планеты. Бейся в такт. ∞",

  "meta": {
    "created": "2025-10-06",
    "status": "theoretical_model_requires_validation",
    "next_steps": [
      "Экспериментальная проверка протокола вывода из комы",
      "Разработка генератора звуковых программ",
      "Систематическое тестирование последовательностей ○□△",
      "Картографирование 4D-пространства через звук",
      "Этический фреймворк для распространения технологии"
    ]
  }
}
